{
  "baseOptions": {
    "description": "Generated by https://archipelago.gg/",
    "game": "Minecraft",
    "name": "Player"
  },
  "gameOptions": {
    "progression_balancing": {
      "type": "special_range",
      "displayName": "Progression Balancing",
      "description": "A system that can move progression earlier, to try and prevent the player from getting stuck and bored early.\nA lower setting means more getting stuck. A higher setting means less getting stuck.",
      "defaultValue": 50,
      "min": 0,
      "max": 99,
      "value_names": {
        "disabled": 0,
        "normal": 50,
        "extreme": 99
      }
    },
    "accessibility": {
      "type": "select",
      "displayName": "Accessibility",
      "description": "Set rules for reachability of your items/locations.\nLocations: ensure everything can be reached and acquired.\nItems: ensure all logically relevant items can be acquired.\nMinimal: ensure what is needed to reach your goal can be acquired.",
      "defaultValue": "items",
      "options": [
        {
          "name": "Locations",
          "value": "locations"
        },
        {
          "name": "Items",
          "value": "items"
        },
        {
          "name": "Minimal",
          "value": "minimal"
        }
      ]
    },
    "priority_locations": {
      "type": "locations-list",
      "displayName": "Priority Locations",
      "description": "Prevent these locations from having an unimportant item"
    },
    "advancement_goal": {
      "type": "range",
      "displayName": "Advancement Goal",
      "description": "Number of advancements required to spawn bosses.",
      "defaultValue": 40,
      "min": 0,
      "max": 95
    },
    "egg_shards_required": {
      "type": "range",
      "displayName": "Egg Shards Required",
      "description": "Number of dragon egg shards to collect to spawn bosses.",
      "defaultValue": 0,
      "min": 0,
      "max": 40
    },
    "egg_shards_available": {
      "type": "range",
      "displayName": "Egg Shards Available",
      "description": "Number of dragon egg shards available to collect.",
      "defaultValue": 0,
      "min": 0,
      "max": 40
    },
    "required_bosses": {
      "type": "select",
      "displayName": "Required Bosses",
      "description": "Bosses which must be defeated to finish the game.",
      "defaultValue": "ender_dragon",
      "options": [
        {
          "name": "None",
          "value": "none"
        },
        {
          "name": "Ender Dragon",
          "value": "ender_dragon"
        },
        {
          "name": "Wither",
          "value": "wither"
        },
        {
          "name": "Both",
          "value": "both"
        }
      ]
    },
    "shuffle_structures": {
      "type": "select",
      "displayName": "Shuffle Structures",
      "description": "Enables shuffling of villages, outposts, fortresses, bastions, and end cities.",
      "defaultValue": "true",
      "options": [
        {
          "name": "No",
          "value": "false"
        },
        {
          "name": "Yes",
          "value": "true"
        }
      ]
    },
    "structure_compasses": {
      "type": "select",
      "displayName": "Structure Compasses",
      "description": "Adds structure compasses to the item pool, which point to the nearest indicated structure.",
      "defaultValue": "true",
      "options": [
        {
          "name": "No",
          "value": "false"
        },
        {
          "name": "Yes",
          "value": "true"
        }
      ]
    },
    "bee_traps": {
      "type": "range",
      "displayName": "Bee Trap Percentage",
      "description": "Replaces a percentage of junk items with bee traps, which spawn multiple angered bees around every player when\nreceived.",
      "defaultValue": 0,
      "min": 0,
      "max": 100
    },
    "combat_difficulty": {
      "type": "select",
      "displayName": "Combat Difficulty",
      "description": "Modifies the level of items logically required for exploring dangerous areas and fighting bosses.",
      "defaultValue": "normal",
      "options": [
        {
          "name": "Easy",
          "value": "easy"
        },
        {
          "name": "Normal",
          "value": "normal"
        },
        {
          "name": "Hard",
          "value": "hard"
        }
      ]
    },
    "include_hard_advancements": {
      "type": "select",
      "displayName": "Include Hard Advancements",
      "description": "Enables certain RNG-reliant or tedious advancements.",
      "defaultValue": "false",
      "options": [
        {
          "name": "No",
          "value": "false"
        },
        {
          "name": "Yes",
          "value": "true"
        }
      ]
    },
    "include_unreasonable_advancements": {
      "type": "select",
      "displayName": "Include Unreasonable Advancements",
      "description": "Enables the extremely difficult advancements \"How Did We Get Here?\" and \"Adventuring Time.\"",
      "defaultValue": "false",
      "options": [
        {
          "name": "No",
          "value": "false"
        },
        {
          "name": "Yes",
          "value": "true"
        }
      ]
    },
    "include_postgame_advancements": {
      "type": "select",
      "displayName": "Include Postgame Advancements",
      "description": "Enables advancements that require spawning and defeating the required bosses.",
      "defaultValue": "false",
      "options": [
        {
          "name": "No",
          "value": "false"
        },
        {
          "name": "Yes",
          "value": "true"
        }
      ]
    },
    "send_defeated_mobs": {
      "type": "select",
      "displayName": "Send Defeated Mobs",
      "description": "Send killed mobs to other Minecraft worlds which have this option enabled.",
      "defaultValue": "false",
      "options": [
        {
          "name": "No",
          "value": "false"
        },
        {
          "name": "Yes",
          "value": "true"
        }
      ]
    },
    "death_link": {
      "type": "select",
      "displayName": "Death Link",
      "description": "When you die, everyone dies. Of course the reverse is true too.",
      "defaultValue": "false",
      "options": [
        {
          "name": "No",
          "value": "false"
        },
        {
          "name": "Yes",
          "value": "true"
        }
      ]
    }
  }
}